pyfallback/__init__.py
pyfallback/fallback.py
pyfallback-0.1.0.dist-info/LICENSE
pyfallback-0.1.0.dist-info/METADATA
pyfallback-0.1.0.dist-info/WHEEL
pyfallback-0.1.0.dist-info/RECORD
