Metadata-Version: 2.1
Name: pyfallback
Version: 0.1.0
Summary: Provides fallback for operations in python
Home-page: https://github.com/weilueluo/pyfallback
License: Apache-2.0
Keywords: fallback,pyfallback
Author: Weilue Luo
Author-email: luoweilue@gmail.com
Requires-Python: >=3.7
Classifier: Intended Audience :: Developers
Classifier: License :: OSI Approved :: Apache Software License
Classifier: Programming Language :: Python :: 3
Classifier: Programming Language :: Python :: 3.7
Classifier: Programming Language :: Python :: 3.8
Classifier: Programming Language :: Python :: 3.9
Classifier: Programming Language :: Python :: 3.10
Classifier: Programming Language :: Python :: 3.11
Project-URL: Repository, https://github.com/weilueluo/pyfallback
